LICENSE
MANIFEST.in
README.rst
cuke-comparison.txt
setup.py
todo.txt
examples/__init__.py
examples/befriending/friends.py
examples/befriending/features/befriending.feature
examples/befriending/features/steps.py
examples/befriending_many/friends.py
examples/befriending_many/features/befriending_many.feature
examples/befriending_many/features/steps.py
examples/calc/calculator.py
examples/calc/features/addition.feature
examples/calc/features/division.feature
examples/calc/features/steps.py
examples/calc_fr/calculator.py
examples/calc_fr/features/addition.feature
examples/calc_fr/features/division.feature
examples/calc_fr/features/steps.py
examples/counter_independence/README.textile
examples/counter_independence/__init__.py
examples/counter_independence/counter.py
examples/counter_independence/features/__init__.py
examples/counter_independence/features/independent_four.feature
examples/counter_independence/features/independent_one.feature
examples/counter_independence/features/independent_one_steps.py
examples/counter_independence/features/independent_three.feature
examples/counter_independence/features/independent_two.feature
examples/counter_independence/features/step/__init__.py
examples/counter_independence/features/step/independent_two_steps.py
examples/docu/__init__.py
examples/docu/document.py
examples/docu/features/__init__.py
examples/docu/features/destruction.feature
examples/docu/features/navigation.feature
examples/docu/features/step/__init__.py
examples/docu/features/step/page_steps.py
examples/self_test/README.textile
examples/self_test/__init__.py
examples/self_test/features/__init__.py
examples/self_test/features/basic_sample.feature
examples/self_test/features/calculator.feature
examples/self_test/features/call_undefined_step_from_step_def.feature
examples/self_test/features/failing_expectation.feature
examples/self_test/features/lots_of_undefined.feature
examples/self_test/features/non-ascii.feature
examples/self_test/features/outline_sample.feature
fresher.egg-info/PKG-INFO
fresher.egg-info/SOURCES.txt
fresher.egg-info/dependency_links.txt
fresher.egg-info/entry_points.txt
fresher.egg-info/requires.txt
fresher.egg-info/top_level.txt
