Metadata-Version: 1.1
Name: fresher
Version: 0.4.2
Summary: Clone of the Cucumber BDD framework for Python forked from Freshen
Home-page: http://github.com/lddubeau/fresher
Author: Louis-Dominique Dubeau
Author-email: ldd@lddubeau.com
License: GPL
Platform: UNKNOWN
Classifier: Development Status :: 4 - Beta
Classifier: Environment :: Plugins
Classifier: Intended Audience :: Developers
Classifier: License :: OSI Approved :: GNU General Public License v3 or later (GPLv3+)
Classifier: Operating System :: OS Independent
Classifier: Programming Language :: Python :: 2.7
Classifier: Programming Language :: Python :: 3.7
Classifier: Topic :: Software Development :: Quality Assurance
Classifier: Topic :: Software Development :: Testing
